airwing_gwc
