Metadata-Version: 1.1
Name: airwing-gwc
Version: 1.0.10
Summary: this is a package for auto generating tile layers in geosever
Home-page: https://github.com/surongxiang/airwing_gwc
Author: wushi
Author-email: hfutsrx@gmail.com
License: MIT
Keywords: geoserver python
Platform: UNKNOWN
Classifier: License :: OSI Approved :: MIT License
Classifier: Programming Language :: Python
Classifier: Intended Audience :: Developers
Classifier: Operating System :: MacOS :: MacOS X
